ynabkit/__init__.py
ynabkit/__main__.py
ynabkit/cli.py
ynabkit/payee.py
ynabkit/fineco/__init__.py
ynabkit/fineco/inputs.py
ynabkit/fineco/models.py
ynabkit/fineco/outputs.py
ynabkit/n26/__init__.py
ynabkit/n26/inputs.py
ynabkit/n26/models.py
ynabkit/n26/outputs.py
ynabkit/satispay/__init__.py
ynabkit/satispay/inputs.py
ynabkit/satispay/models.py
ynabkit/satispay/outputs.py
ynabkit-0.4.2.dist-info/licenses/LICENSE
ynabkit-0.4.2.dist-info/METADATA
ynabkit-0.4.2.dist-info/WHEEL
ynabkit-0.4.2.dist-info/entry_points.txt
ynabkit-0.4.2.dist-info/top_level.txt
ynabkit-0.4.2.dist-info/RECORD
