Metadata-Version: 2.4
Name: ynabkit
Version: 0.4.2
Summary: CLI tool to support data import and export from YNAB
Home-page: https://github.com/zmoog/ynabkit
Author: Maurizio Branca
License: Apache License, Version 2.0
Project-URL: Issues, https://github.com/zmoog/ynabkit/issues
Project-URL: CI, https://github.com/zmoog/ynabkit/actions
Project-URL: Changelog, https://github.com/zmoog/ynabkit/releases
Requires-Python: >=3.10
License-File: LICENSE
Requires-Dist: click
Requires-Dist: openpyxl
Requires-Dist: PyYAML
Requires-Dist: rich
Requires-Dist: xlrd
Provides-Extra: test
Requires-Dist: pytest; extra == "test"
Dynamic: author
Dynamic: description
Dynamic: description-content-type
Dynamic: home-page
Dynamic: license
Dynamic: license-file
Dynamic: project-url
Dynamic: provides-extra
Dynamic: requires-dist
Dynamic: requires-python
Dynamic: summary
